LICENSE.txt
README.md
setup.cfg
setup.py
autotda/__init__.py
autotda/autofeat_class.py
autotda.egg-info/PKG-INFO
autotda.egg-info/SOURCES.txt
autotda.egg-info/dependency_links.txt
autotda.egg-info/requires.txt
autotda.egg-info/top_level.txt
autotda/functions/__init__.py
autotda/functions/classes.py
autotda/functions/evaluation_functions.py
autotda/functions/feature_functions.py
autotda/functions/helper_functions.py
autotda/functions/relationship_functions.py
autotda/functions/tree_functions.py